Metadata-Version: 2.1
Name: nonebot-plugin-fr24
Version: 0.2.2
Summary: nonebot2航班查询
Home-page: https://github.com/IronWolf-K/nonebot_plugin_fr24
Author: IronW
Author-email: jhhh5hj@hotmail.com
License: UNKNOWN
Platform: UNKNOWN
